ccolors.py
ccolors-1.0.0.dist-info/WHEEL
ccolors-1.0.0.dist-info/METADATA
ccolors-1.0.0.dist-info/RECORD
